business_validator-2.0.1.dist-info/METADATA
business_validator-2.0.1.dist-info/WHEEL
business_validator-2.0.1.dist-info/licenses/LICENSE
business_validator/__init__.py
business_validator/types.py
business_validator/utils.py
business_validator/validator.py
examples/__init__.py
examples/multiple_error.py
examples/single_error.py
examples/types.py
business_validator-2.0.1.dist-info/RECORD
